xarg/__init__.py
xarg/actuator.py
xarg/attribute.py
xarg/colorful.py
xarg/complete.py
xarg/logger.py
xarg/parser.py
xarg/project.py
xarg/safefile.py
xarg/scanner.py
xarg/sheet.py
xarg/thread.py
xarg/utils.py
xarg/unittest/__init__.py
xarg/unittest/test_actuator.py
xarg/unittest/test_colorful.py
xarg/unittest/test_parser.py
xarg/unittest/test_safefile.py
xarg/unittest/test_scanner.py
xarg/unittest/test_sheet.py
xarg/unittest/test_util.py
xarg_python-1.8.0.dist-info/LICENSE
xarg_python-1.8.0.dist-info/METADATA
xarg_python-1.8.0.dist-info/WHEEL
xarg_python-1.8.0.dist-info/entry_points.txt
xarg_python-1.8.0.dist-info/top_level.txt
xarg_python-1.8.0.dist-info/zip-safe
xarg_python-1.8.0.dist-info/RECORD
